{
  "id": "B19PIFPRODUCT_TYPE_SKIN_CA",
  "product_reference": "B19PRDPRODUCT_TYPE_SKIN_CA",
  "formulation_reference": "B19FRMPRODUCT_TYPE_SKIN_CA",
  "document_metadata": {
    "filename": "PIF - Zone - (8 Products) - 3 of 3 - 2021_08.pdf",
    "format": "pdf",
    "extraction_date": "2025-11-08T03:04:21.189Z"
  },
  "product_info": {
    "name": "Product type Skin care",
    "type": "Unknown",
    "form": "Unknown",
    "color": "Unknown",
    "pack_size": "Unknown",
    "manufacturer_code": "daily",
    "normal_use": "daily"
  },
  "ingredients_count": 1
}